pmi_clang_format-19.1.0.2.dist-info/METADATA
pmi_clang_format-19.1.0.2.dist-info/entry_points.txt
pmi_clang_format-19.1.0.2.dist-info/RECORD
pmi_clang_format-19.1.0.2.dist-info/WHEEL
pmi_clang_format-19.1.0.2.dist-info/licenses/LICENSE.md
pmi_clang_format-19.1.0.2.dist-info/licenses/COPYING.md
pmi_clang_format.libs/libstdc++-496613c0.so.6.0.32
pmi_clang_format.libs/libgcc_s-a3a07607.so.1
clang_format/git_clang_format.py
clang_format/clang_format_diff.py
clang_format/__init__.py
clang_format/data/bin/clang-format
