Metadata-Version: 2.1
Name: pmi-clang-format
Version: 19.1.0.2
Summary: Clang-Format is an LLVM-based code formatting tool
Author-Email: Walid Boussafa <walid.boussafa@outlook.com>
License: Apache 2.0
Classifier: Programming Language :: C
Classifier: Programming Language :: C++
Classifier: Operating System :: OS Independent
Classifier: License :: OSI Approved :: Apache Software License
Classifier: Intended Audience :: Developers
Classifier: Topic :: Software Development :: Quality Assurance
Project-URL: Clang, http://clang.llvm.org/
Project-URL: Documentation, https://clang.llvm.org/docs/ClangFormat.html
Project-URL: Download, https://github.com/llvm/llvm-project/releases
Project-URL: Source, https://github.com/ssciwr/clang-format-wheel
